revault/__init__.py
revault/comp.py
revault/database.py
revault/entry.py
revault/key.py
revault/store.py
revault-0.2.0.dist-info/METADATA
revault-0.2.0.dist-info/WHEEL
revault-0.2.0.dist-info/RECORD
