Metadata-Version: 2.1
Name: revault
Version: 0.2.0
Summary: 
Author: Ada Bohm
Author-email: ada@kreatrix.org
Requires-Python: >=3.10,<4.0
Classifier: Programming Language :: Python :: 3
Classifier: Programming Language :: Python :: 3.10
Classifier: Programming Language :: Python :: 3.11
Classifier: Programming Language :: Python :: 3.12
Requires-Dist: sqlalchemy (>=2.0.30,<3.0.0)
